structconf/__init__.py
structconf/conf.py
structconf-0.3.0.dist-info/LICENSE
structconf-0.3.0.dist-info/WHEEL
structconf-0.3.0.dist-info/METADATA
structconf-0.3.0.dist-info/RECORD
